{
    "kind": "List",
    "apiVersion": "v1",
    "metadata": {
        "name": "amq63-image-stream",
        "annotations": {
            "description": "ImageStream definition for Red Hat JBoss AMQ 6.3.",
            "openshift.io/provider-display-name": "Red Hat, Inc."
        }
    },
    "items": [
        {
            "kind": "ImageStream",
            "apiVersion": "v1",
            "metadata": {
                "name": "jboss-amq-63",
                "annotations": {
                    "openshift.io/display-name": "Red Hat JBoss A-MQ 6.3",
                    "openshift.io/provider-display-name": "Red Hat, Inc.",
                    "version": "1.4-48"
                }
            },
            "labels": {
                "xpaas": "1.4-48"
            },
            "spec": {
                "tags": [
                    {
                        "name": "1.4",
                        "annotations": {
                            "description": "JBoss A-MQ 6.3 broker image.",
                            "iconClass": "icon-amq",
                            "tags": "messaging,amq,jboss,hidden",
                            "supports": "amq:6.3,messaging",
                            "version": "1.4",
                            "openshift.io/display-name": "Red Hat JBoss A-MQ 6.3"
                        },
                        "referencePolicy": {
                            "type": "Local"
                        },
                        "from": {
                            "kind": "DockerImage",
                            "name": "registry.redhat.io/jboss-amq-6/amq63-openshift:1.4"
                        }
                    },
                    {
                        "name": "latest",
                        "annotations": {
                            "description": "JBoss A-MQ 6.3 broker image.",
                            "iconClass": "icon-amq",
                            "tags": "messaging,amq,jboss,hidden",
                            "supports": "amq:6.3,messaging",
                            "version": "latest",
                            "openshift.io/display-name": "Red Hat JBoss A-MQ 6.3"
                        },
                        "referencePolicy": {
                            "type": "Local"
                        },
                        "from": {
                            "kind": "DockerImage",
                            "name": "registry.redhat.io/jboss-amq-6/amq63-openshift:latest"
                        }
                    }
                ]
            }
        }
    ]
}
